stadfangaskra/__init__.py
stadfangaskra/lookup.py
stadfangaskra/matches.py
stadfangaskra/parser.py
stadfangaskra/static.py
py_stadfangaskra-1.0.0.dist-info/METADATA
py_stadfangaskra-1.0.0.dist-info/WHEEL
py_stadfangaskra-1.0.0.dist-info/top_level.txt
py_stadfangaskra-1.0.0.dist-info/RECORD
