Metadata-Version: 2.1
Name: py-stadfangaskra
Version: 1.0.0
Summary: Icelandic Location Registry utils
Home-page: https://github.com/StefanKjartansson/py-stadfangaskra
Author: Stefán Kjartansson
Author-email: stefan.mar.kjartansson@gmail.com
License: UNKNOWN
Platform: UNKNOWN
Classifier: License :: OSI Approved :: MIT License
Classifier: Programming Language :: Python
Classifier: Programming Language :: Python :: 3
Classifier: Programming Language :: Python :: Implementation :: CPython
Requires-Python: >=3.5
Requires-Dist: pandas (>=1.0.3)
Requires-Dist: geopandas (>=0.7.0)
Requires-Dist: dataclasses ; python_version<'3.7'
Provides-Extra: dev
Requires-Dist: ipython ; extra == 'dev'
Requires-Dist: coverage ; extra == 'dev'
Requires-Dist: pytest-cov ; extra == 'dev'
Requires-Dist: pytest-env ; extra == 'dev'
Requires-Dist: pytest ; extra == 'dev'
Requires-Dist: pylint ; extra == 'dev'
Requires-Dist: black ; (python_version>="3.6") and extra == 'dev'
